{
	"name":"1531ИР22",
	"num_pins": 20,
	"height": 25,
	"width": 25,
	"texture": "res://graphics/legacy/ic/20leg_2x.png",
	"pinSpecifications": [
		{
			"index": 1,
			"direction": "DIRECTION_INPUT",
			"position": "BOTTOM",
			"readable_name": "~En",
			"description": "Enable",
			"dependencies": []
		},{
			"index": 2,
			"direction": "DIRECTION_OUTPUT",
			"position": "BOTTOM",
			"readable_name": "Q0",
			"description": "Выход данных",
			"dependencies": [-1]
		},{
			"index": 3,
			"direction": "DIRECTION_INPUT",
			"position": "BOTTOM",
			"readable_name": "D0",
			"description": "Вход данных",
			"dependencies": []
		}
		,{
			"index": 4,
			"direction": "DIRECTION_INPUT",
			"position": "BOTTOM",
			"readable_name": "D1",
			"description": "Вход данных",
			"dependencies": []
		},{
			"index": 5,
			"direction": "DIRECTION_OUTPUT",
			"position": "BOTTOM",
			"readable_name":"Q1",
			"description": "Выход данных",
			"dependencies": [-1]
		},{
			"index": 6,
			"direction": "DIRECTION_OUTPUT",
			"position": "BOTTOM",
			"readable_name": "Q2",
			"description": "Выход данных",
			"dependencies": [-1]
		}
		,{
			"index": 7,
			"direction": "DIRECTION_INPUT",
			"position": "BOTTOM",
			"readable_name": "D2",
			"description": "Вход данных",
			"dependencies": []
		}
		,{
			"index": 8,
			"direction": "DIRECTION_INPUT",
			"position": "BOTTOM",
			"readable_name": "D3",
			"description": "Вход данных",
			"dependencies": []
		},{
			"index": 9,
			"direction": "DIRECTION_OUTPUT",
			"position": "BOTTOM",
			"readable_name": "Q3",
			"description": "Выход данных",
			"dependencies": [-1]
		}
		,{
			"index": 10,
			"direction": "DIRECTION_OUTPUT",
			"position": "BOTTOM",
			"readable_name": "GND",
			"description": "Земля",
			"dependencies": []
		}
		,{
			"index": 20,
			"direction": "DIRECTION_OUTPUT",
			"position": "TOP",
			"readable_name": "VCC",
			"description": "Питание 5В",
			"dependencies": []
		}
		,{
			"index": 19,
			"direction": "DIRECTION_OUTPUT",
			"position": "TOP",
			"readable_name": "Q7",
			"description": "Выход данных",
			"dependencies": [-1]
		},{
			"index": 18,
			"direction": "DIRECTION_INPUT",
			"position": "TOP",
			"readable_name": "D7",
			"description": "Вход данных",
			"dependencies": []
		},{
			"index": 17,
			"direction": "DIRECTION_INPUT",
			"position": "TOP",
			"readable_name": "D6",
			"description": "Вход данных",
			"dependencies": []
		}
		,{
			"index": 16,
			"direction": "DIRECTION_OUTPUT",
			"position": "TOP",
			"readable_name": "Q6",
			"description": "Выход данных",
			"dependencies": [-1]
		}
		,{
			"index": 15,
			"direction": "DIRECTION_OUTPUT",
			"position": "TOP",
			"readable_name": "Q5",
			"description": "Выход данных",
			"dependencies": []
		}
		,{
			"index": 14,
			"direction": "DIRECTION_INPUT",
			"position": "TOP",
			"readable_name": "D5",
			"description": "Вход данных",
			"dependencies": []
		},{
			"index": 13,
			"direction": "DIRECTION_INPUT",
			"position": "TOP",
			"readable_name": "C",
			"description": "Вход синхронизации по уровню",
			"dependencies": []
		},{
			"index": 12,
			"direction": "DIRECTION_OUTPUT",
			"position": "TOP",
			"readable_name": "Q4",
			"description": "Выход данных",
			"dependencies": [-1]
		}
		,{
			"index": 11,
			"direction": "DIRECTION_INPUT",
			"position": "TOP",
			"readable_name": "D4",
			"description": "Вход данных",
			"dependencies": []
		}
	]
}
